sharepoint_uploader/__init__.py
sharepoint_uploader/logger.py
sharepoint_uploader/uploader.py
sharepoint_uploader-1.0.4.dist-info/METADATA
sharepoint_uploader-1.0.4.dist-info/WHEEL
sharepoint_uploader-1.0.4.dist-info/top_level.txt
sharepoint_uploader-1.0.4.dist-info/RECORD
